MANIFEST.in
README.rst
setup.py
aliyun_python_sdk_acs_test.egg-info/PKG-INFO
aliyun_python_sdk_acs_test.egg-info/SOURCES.txt
aliyun_python_sdk_acs_test.egg-info/dependency_links.txt
aliyun_python_sdk_acs_test.egg-info/requires.txt
aliyun_python_sdk_acs_test.egg-info/top_level.txt
aliyunsdkacs/__init__.py
aliyunsdkacs/request/__init__.py
aliyunsdkacs/request/v20150101/DeleteApiInDailyRequest.py
aliyunsdkacs/request/v20150101/DeleteApiOnlineRequest.py
aliyunsdkacs/request/v20150101/ModifyApiNameInDailyRequest.py
aliyunsdkacs/request/v20150101/ModifyApiNameRequest.py
aliyunsdkacs/request/v20150101/PurchaseApiRequest.py
aliyunsdkacs/request/v20150101/PutFlowControlRequest.py
aliyunsdkacs/request/v20150101/ResumePurchasedApiRequest.py
aliyunsdkacs/request/v20150101/StopPurchasedApiRequest.py
aliyunsdkacs/request/v20150101/__init__.py